gitbuilding/__init__.py
gitbuilding/__main__.py
gitbuilding/config.py
gitbuilding/example.py
gitbuilding/generate_ci.py
gitbuilding/gui.py
gitbuilding/handler.py
gitbuilding/live_editor.py
gitbuilding/markdown_latex.py
gitbuilding/native_file_operations.py
gitbuilding/output.py
gitbuilding/previewers.py
gitbuilding/render.py
gitbuilding/server.py
gitbuilding/server_utils.py
gitbuilding/utilities.py
gitbuilding/buildup/__init__.py
gitbuilding/buildup/basepart.py
gitbuilding/buildup/buildup.py
gitbuilding/buildup/buildup_list.py
gitbuilding/buildup/config.py
gitbuilding/buildup/core.py
gitbuilding/buildup/exsource.py
gitbuilding/buildup/files.py
gitbuilding/buildup/libraries.py
gitbuilding/buildup/link.py
gitbuilding/buildup/markdown_extensions.py
gitbuilding/buildup/page.py
gitbuilding/buildup/pageorder.py
gitbuilding/buildup/partlist.py
gitbuilding/buildup/parts.py
gitbuilding/buildup/preview.py
gitbuilding/buildup/quantity.py
gitbuilding/buildup/unit.py
gitbuilding/buildup/unmark.py
gitbuilding/buildup/url.py
gitbuilding/buildup/utilities.py
gitbuilding/licenses/AGPL-3.0.txt
gitbuilding/licenses/Apache-2.0.txt
gitbuilding/licenses/BSD-2-Clause.txt
gitbuilding/licenses/BSD-3-Clause.txt
gitbuilding/licenses/CC-BY-3.0.txt
gitbuilding/licenses/CC-BY-4.0.txt
gitbuilding/licenses/CC-BY-SA-3.0.txt
gitbuilding/licenses/CC-BY-SA-4.0.txt
gitbuilding/licenses/CERN-OHL-1.1.txt
gitbuilding/licenses/CERN-OHL-1.2.txt
gitbuilding/licenses/CERN-OHL-P-2.0.txt
gitbuilding/licenses/CERN-OHL-S-2.0.txt
gitbuilding/licenses/CERN-OHL-W-2.0.txt
gitbuilding/licenses/EPL-1.0.txt
gitbuilding/licenses/GPL-2.0.txt
gitbuilding/licenses/GPL-3.0.txt
gitbuilding/licenses/LGPL-2.1.txt
gitbuilding/licenses/LGPL-3.0.txt
gitbuilding/licenses/MIT.txt
gitbuilding/licenses/MPL-2.0.txt
gitbuilding/licenses/SHL-0.5.txt
gitbuilding/licenses/SHL-0.51.txt
gitbuilding/licenses/SHL-2.0.txt
gitbuilding/licenses/TAPR-OHL-1.0.txt
gitbuilding/licenses/Unlicense.txt
gitbuilding/static/3d-viewer.js
gitbuilding-0.14.9.dist-info/LICENSE
gitbuilding-0.14.9.dist-info/METADATA
gitbuilding-0.14.9.dist-info/WHEEL
gitbuilding-0.14.9.dist-info/entry_points.txt
gitbuilding-0.14.9.dist-info/top_level.txt
gitbuilding-0.14.9.dist-info/RECORD
