Metadata-Version: 2.1
Name: gitbuilding
Version: 0.14.9
Summary: For documenting hardware projects with minimal effort,so you can stop writing and GitBuilding.
Home-page: https://gitbuilding.io/
Author: Julian Stirling
Author-email: julian@julianstirling.co.uk
License: GPLv3
Project-URL: Bug Tracker, https://gitlab.com/gitbuilding/gitbuilding/issues
Project-URL: Source Code, https://gitlab.com/gitbuilding/gitbuilding
Keywords: Documentation,Hardware
Classifier: Development Status :: 5 - Production/Stable
Classifier: License :: OSI Approved :: GNU General Public License v3 (GPLv3)
Classifier: Programming Language :: Python :: 3.8
Requires-Python: >=3.8
License-File: LICENSE
Requires-Dist: argparse
Requires-Dist: pyyaml >=5.1
Requires-Dist: python-frontmatter
Requires-Dist: flask
Requires-Dist: flask-cors
Requires-Dist: requests
Requires-Dist: markdown >=3.2
Requires-Dist: latex2mathml
Requires-Dist: colorama
Requires-Dist: marshmallow >=03.22
Requires-Dist: jinja2
Requires-Dist: regex >=2022.1.18
Requires-Dist: waitress
Requires-Dist: defusedxml >=0.7.1
Requires-Dist: pygments >=2.14
Requires-Dist: pathspec >=0.11
Requires-Dist: watchdog >=3.0
Requires-Dist: exsource-tools ==0.0.6
Requires-Dist: weasyprint >=60.1
Provides-Extra: dev
Requires-Dist: pylint <=3.1 ; extra == 'dev'
Requires-Dist: coverage ; extra == 'dev'
Requires-Dist: curlylint ; extra == 'dev'
Requires-Dist: pydeps ; extra == 'dev'
Requires-Dist: twine ; extra == 'dev'
Provides-Extra: gui
Requires-Dist: PyQt5 ; extra == 'gui'
Requires-Dist: PyQtWebEngine ; extra == 'gui'
